AutoUpdateGit/__init__.py
AutoUpdateGit/autoupdategit.py
AutoUpdateGit-1.2.dist-info/METADATA
AutoUpdateGit-1.2.dist-info/WHEEL
AutoUpdateGit-1.2.dist-info/top_level.txt
AutoUpdateGit-1.2.dist-info/RECORD
