Metadata-Version: 2.1
Name: AutoUpdateGit
Version: 1.2
Summary: Make your program autoupdate with Github Raw
Home-page: https://github.com/Nelliprav/AutoUpdateGit
Author: LunaModules
Author-email: probeb589@gmail.com
Classifier: Programming Language :: Python :: 3
Classifier: License :: OSI Approved :: MIT License
Classifier: Operating System :: OS Independent
Requires-Python: >=3.6
